{"results": [{"expected": 47, "actual": 47, "correct?": true}, {"expected": 96, "actual": 96, "correct?": true}, {"expected": 35, "actual": 35, "correct?": true}, {"expected": 8, "actual": 8, "correct?": true}, {"expected": 82, "actual": 82, "correct?": true}, {"expected": 82, "actual": 82, "correct?": true}, {"expected": 53, "actual": 53, "correct?": true}, {"expected": 16, "actual": 16, "correct?": true}, {"expected": 15, "actual": 15, "correct?": true}, {"expected": 37, "actual": 37, "correct?": true}, {"expected": 1, "actual": 1, "correct?": true}], "max_score": 4, "actual_score": 4}